measuresUnite/__init__.py
measuresUnite/measure.py
measuresUnite/models.py
measuresUnite/unit.py
measuresUnite/src/__init__.py
measuresUnite/src/unit_systems/__init__.py
measuresUnite/src/unit_systems/si.py
measuresUnite/src/utils/__init__.py
measuresUnite/src/utils/constants.py
measuresUnite/src/utils/converter.py
measuresUnite/src/utils/process.py
measuresUnite-0.0.3.dist-info/METADATA
measuresUnite-0.0.3.dist-info/WHEEL
measuresUnite-0.0.3.dist-info/top_level.txt
measuresUnite-0.0.3.dist-info/RECORD
